{"game_name":"Street Fighter 3 Alpha","move_types":{"special":"green","super-combo":"red","max-super-combo":"blue"},"characters":[{"name":"Adon","moves":[{"name":"Rising Jaguar","type":"special","exec":"[623]+[k]","note":"","prereq":""},{"name":"Jaguar Kick","type":"special","exec":"<AIR>[k]","note":"","prereq":"X-ism"},{"name":"Jaguar Kick","type":"special","exec":"[421]+[k]","note":"","prereq":"X-ism & V-ism"},{"name":"Jaguar Tooth","type":"special","exec":"[63214]+[k]","note":"","prereq":""},{"name":"Jaguar Varied Assault","type":"super-combo","exec":"[236][2][3]+[p]","note":"","prereq":"X-ism & A-ism"},{"name":"Jaguar Revolver","type":"super-combo","exec":"[236][236]+[k]","note":"","prereq":"A-ism"}]},{"name":"Akuma","moves":[{"name":"Gohadoken","type":"special","exec":"[236]+[p]","note":"","prereq":""},{"name":"Shakunetsu Hadoken","type":"special","exec":"[63214]+[p]","note":"","prereq":""},{"name":"Zanku Hadoken","type":"special","exec":"<AIR>[236]+[p]","note":"","prereq":""},{"name":"Goshoryuken","type":"special","exec":"[623]+[p]","note":"","prereq":""},{"name":"Tatsumaki Zankukyaku ","type":"special","exec":"[214]+[k]","note":"AIR OKAY","prereq":""},{"name":"Hyakkishu","type":"special","exec":"[1][236][9]+[p]","note":"","prereq":"A-ism & V-ism"},{"name":"Zenpou Tenshin","type":"special","exec":"[214]+[p]","note":"","prereq":"A-ism & V-ism"},{"name":"Ashura Senku","type":"special","exec":"<[623]/[421]>+<[3p]/[3k]>","note":"","prereq":""},{"name":"Messatsu Gou Hado","type":"super-combo","exec":"[63214][63214]+[p]","note":"","prereq":"A-ism"},{"name":"Messatsu Gou Shouryuu","type":"super-combo","exec":"[236][2][3]+[p]","note":"","prereq":"A-ism"},{"name":"Tenma Gou Zankuu","type":"super-combo","exec":"<AIR>[236][236]+[p]","note":"","prereq":"A-ism"},{"name":"Shun Goku Satsu","type":"max-super-combo","exec":"[lp][lp][6][lk][hp]","note":"","prereq":"X-ism & A-ism"}]},{"name":"Balrog","moves":[{"name":"Dash Straight","type":"special","exec":"[h4][6]+[p]","note":"","prereq":""},{"name":"Dash Upper","type":"special","exec":"[h4][6]+[k]","note":"","prereq":""},{"name":"Dash Ground Straight","type":"special","exec":"[h4][3]+[p]","note":"","prereq":"A-ism & V-ism"},{"name":"Dash Ground Upper","type":"special","exec":"[h4][3]+[k]","note":"","prereq":"A-ism & V-ism"},{"name":"Buffalo Head","type":"special","exec":"[h2][8]+[p]","note":"A-ism version is Reversal Only","prereq":"A-ism & V-ism"},{"name":"Turn Punch","type":"special","exec":"<HOLD[3p]/[3k]>","note":"Can be Charged","prereq":""},{"name":"Crazy Buffalo","type":"super-combo","exec":"[h4][6][4][6]+<[p]/[k]>","note":"","prereq":"X-ism"},{"name":"Crazy Buffalo","type":"super-combo","exec":"[h4][6][4][6]+[p]","note":"","prereq":"A-ism"},{"name":"Gigaton Blow","type":"max-super-combo","exec":"[h4][6][4][6]+[k]","note":"","prereq":"A-ism"}]},{"name":"Birdie","moves":[{"name":"Bull Head","type":"special","exec":"[h4][6]+[p]","note":"","prereq":""},{"name":"Bull Horn","type":"special","exec":"<HOLD[2p]/[2k]>","note":"Can be Charged","prereq":""},{"name":"Murderer Chain","type":"special","exec":"[63214789]+[p]","note":"","prereq":""},{"name":"Bandit Chain","type":"special","exec":"[63214789]+[k]","note":"","prereq":""},{"name":"The Birdie","type":"super-combo","exec":"[h4][6][4][6]+[p]","note":"","prereq":"X-ism & A-ism"},{"name":"Bull Revenger","type":"super-combo","exec":"[236][2][3]+<[p]/[k]>","note":"","prereq":""}]},{"name":"Blanka","moves":[{"name":"Electric Thunder","type":"special","exec":"<TAP[p]>","note":"","prereq":""},{"name":"Rolling Attack","type":"special","exec":"[h4][6]+[p]","note":"","prereq":""},{"name":"Vertical Roll","type":"special","exec":"[h2][8]+[k]","note":"","prereq":""},{"name":"Backstep Roll","type":"special","exec":"[h4][6]+[k]","note":"","prereq":""},{"name":"Ground Shave Roll","type":"super-combo","exec":"[h4][6][4][6]+[p]","note":"[p] can be Charged","prereq":""},{"name":"Tropical Hazard","type":"super-combo","exec":"[h1][3][1][9]+[k]","note":"Tap [p] or [k] for additional attacks","prereq":""}]},{"name":"Cammy","moves":[{"name":"Spiral Arrow","type":"special","exec":"[236]+[k]","note":"","prereq":""},{"name":"Cannon Spike","type":"special","exec":"[623]+[k]","note":"","prereq":""},{"name":"Axle Spin Knuckle","type":"special","exec":"[63214]+[p]","note":"","prereq":"X-ism & A-ism"},{"name":"Hooligan Combination","type":"special","exec":"[1][236][9]+[p]","note":"","prereq":""},{"name":"Cannon Strike","type":"special","exec":"<AIR>[214]+[k]","note":"while jumping forward","prereq":"V-ism"},{"name":"Cannon Revenge","type":"special","exec":"[214]+[p]","note":"","prereq":"V-ism"},{"name":"Spin Drive Smasher","type":"super-combo","exec":"[236][2][3]+[k]","note":"","prereq":"X-ism & A-ism"},{"name":"Reverse Shaft Breaker","type":"super-combo","exec":"[214][214]+[k](<TAP [p]/[k]>)","note":"","prereq":"A-ism"},{"name":"Killer Bee Assault","type":"max-super-combo","exec":"[h1][3][1][9]+[k]","note":"","prereq":"A-ism"}]},{"name":"Charlie","moves":[{"name":"Sonic Boom","type":"special","exec":"[h4][6]+[p]","note":"","prereq":""},{"name":"Somersault Kick","type":"special","exec":"[h2][8]+[k]","note":"","prereq":""},{"name":"Somersault Justice","type":"super-combo","exec":"[h1][3][1][9]+[k]","note":"","prereq":"X-ism & A-ism"},{"name":"Crossfire Blitz","type":"super-combo","exec":"[h4][6][4][6]+[k]","note":"","prereq":"A-ism"},{"name":"Sonic Break","type":"super-combo","exec":"[h4][6][4][6]+[p](<TAP[p]>)","note":"","prereq":"A-ism"}]},{"name":"Chun-Li","moves":[{"name":"Hyakuretsukyaku","type":"special","exec":"<TAP[k]>","note":"","prereq":""},{"name":"Kikoken","type":"special","exec":"[41236]+[p]","note":"","prereq":"A-ism & V-ism"},{"name":"Sen'en Shuu","type":"special","exec":"[63214]+[k]","note":"","prereq":""},{"name":"Tenshokyaku","type":"special","exec":"[h2][8]+[k]","note":"X-ism version is Reversal Only","prereq":""},{"name":"Spinning Bird Kick","type":"special","exec":"[h4][6]+[k]","note":"AIR OKAY","prereq":"X-ism"},{"name":"Sou Hakkei","type":"special","exec":"[h4][6]+[p]","note":"","prereq":"X-ism"},{"name":"Senretsukyaku","type":"super-combo","exec":"[h4][6][4][6]+[k]","note":"","prereq":"X-ism & A-ism"},{"name":"Hazan Tenshokyaku","type":"super-combo","exec":"[h1][3][1][9]+[k]","note":"","prereq":"X-ism & A-ism"},{"name":"Kikosho","type":"super-combo","exec":"[236][236]+[p]","note":"","prereq":"A-ism"}]},{"name":"Cody","moves":[{"name":"Bad Stone/Knife Throw","type":"special","exec":"[236]+[p]","note":"Hold [p] to Delay, <TAUNT> to feint","prereq":""},{"name":"Ruffian Kick","type":"special","exec":"[236]+[k]","note":"","prereq":""},{"name":"Criminal Upper","type":"special","exec":"[214]+[p]","note":"","prereq":""},{"name":"Knife Pickup","type":"special","exec":"[2]+[2p]","note":"When standing above the knife","prereq":""},{"name":"Bad Spray","type":"special","exec":"[4][1][2]+[p]","note":"When down","prereq":"A-ism & V-ism"},{"name":"Final Destruction","type":"super-combo","exec":"[236][236]+[p]","note":"","prereq":"X-ism & A-ism"},{"name":"Dead End Irony","type":"super-combo","exec":"[236][236]+[k]","note":"","prereq":"A-ism"}]},{"name":"Dan","moves":[{"name":"Gadoken","type":"special","exec":"[236]+[p]","note":"","prereq":""},{"name":"Koryuken","type":"special","exec":"[623]+[p]","note":"","prereq":""},{"name":"Dankukyaku","type":"special","exec":"[214]+[k]","note":"","prereq":""},{"name":"Airborne Dankukyaku","type":"special","exec":"<AIR>[214]+[k]","note":"","prereq":"A-ism & V-ism"},{"name":"Saikyo Defense","type":"special","exec":"[6]+[3p]","note":"While blocking","prereq":"V-ism"},{"name":"Forward Rolling Taunt","type":"special","exec":"[236]+<TAUNT>","note":"","prereq":""},{"name":"Backward Rolling Taunt","type":"special","exec":"[214]+<TAUNT>","note":"","prereq":""},{"name":"Air Taunt","type":"special","exec":"<AIR><TAUNT>","note":"","prereq":""},{"name":"Hissho Buraiken","type":"super-combo","exec":"[214][214]+[k]","note":"","prereq":"X-ism & A-ism"},{"name":"Shinkuu Gadoken","type":"super-combo","exec":"[236][236]+[3p]","note":"","prereq":"A-ism"},{"name":"Koryuu Rekka","type":"super-combo","exec":"[236][2][3]+[k]","note":"","prereq":"A-ism"},{"name":"Legendary Taunt","type":"super-combo","exec":"[236][236]+<TAUNT>","note":"","prereq":"A-ism"},{"name":"Legendary Taunt","type":"max-super-combo","exec":"[214][214]+<TAUNT>","note":"","prereq":"A-ism"}]},{"name":"Dee Jay","moves":[{"name":"Air Slasher","type":"special","exec":"[h4][6]+[p]","note":"","prereq":""},{"name":"Double Rolling Sobat","type":"special","exec":"[h4][6]+[k]","note":"","prereq":""},{"name":"Jackknife Maximum","type":"special","exec":"[h2][8]+[k]","note":"","prereq":""},{"name":"Machine Gun Upper","type":"special","exec":"[h2][8]+[p](<TAP[p]>)","note":"","prereq":""},{"name":"Sobat Carnival","type":"super-combo","exec":"[h4][6][4][6]+[k]","note":"","prereq":"X-ism & A-ism"},{"name":"Climax Break","type":"super-combo","exec":"[h1][3][1][9]+[p]","note":"","prereq":"A-ism"},{"name":"Theme of Sunrise","type":"super-combo","exec":"[h1][3][1][9]+[k]","note":"","prereq":"A-ism"}]},{"name":"Dhalsim","moves":[{"name":"Yoga Fire","type":"special","exec":"[236]+[p]","note":"","prereq":""},{"name":"Yoga Flame","type":"special","exec":"[41236]+[p]","note":"","prereq":""},{"name":"Yoga Blast","type":"special","exec":"[41236]+[k]","note":"","prereq":""},{"name":"Yoga Teleport","type":"special","exec":"<[623]/[421]>+<[3p]/[3k]>","note":"A-ism and V-ism versions are AIR OKAY","prereq":""},{"name":"Yoga Escape","type":"special","exec":"[4][1][2]+[k]","note":"Reversal Only","prereq":"A-ism & V-ism"},{"name":"Yoga Tempest","type":"super-combo","exec":"[41236][41236]+[p]","note":"","prereq":"X-ism"},{"name":"Yoga Inferno","type":"super-combo","exec":"[236][2][3]+[p]","note":"","prereq":"A-ism"},{"name":"Yoga Strike","type":"super-combo","exec":"[236][2][3]+[k]","note":"","prereq":"A-ism"},{"name":"Yoga Stream","type":"super-combo","exec":"[214][214]+[p]","note":"","prereq":"A-ism"}]},{"name":"Eagle","moves":[{"name":"Manchester Black","type":"special","exec":"[214]+[p]","note":"","prereq":""},{"name":"Canterbury Blue","type":"special","exec":"[236]+[p]","note":"Can be Delayed","prereq":""},{"name":"Oxford Red","type":"special","exec":"[41236]+[k]","note":"","prereq":""},{"name":"Liverpool White","type":"special","exec":"[214]+[k]","note":"","prereq":""},{"name":"St. Andrew's Green","type":"special","exec":"[623]+[p]","note":"","prereq":""},{"name":"Union Jack Platinum","type":"super-combo","exec":"[236][236]+[p]","note":"","prereq":"X-ism & A-ism"},{"name":"Manchester Gold","type":"special","exec":"[214][214]+[p]","note":"","prereq":"X-ism & A-ism"}]},{"name":"Edmond Honda","moves":[{"name":"Hundred Hand Slap","type":"special","exec":"<TAP[p]>","note":"","prereq":""},{"name":"Sumo Headbutt","type":"special","exec":"[h4][6]+[p]","note":"","prereq":""},{"name":"Sumo Smash","type":"special","exec":"[h2][8]+[k]","note":"","prereq":""},{"name":"Oicho Throw","type":"special","exec":"[63214789]+[p]","note":"","prereq":""},{"name":"Oni Muso","type":"super-combo","exec":"[h4][6][4][6]+[p]","note":"","prereq":"X-ism & A-ism"},{"name":"Fuji Drop","type":"super-combo","exec":"[h4][6][4][6]+[k]","note":"","prereq":"A-ism"},{"name":"Orochi Crush","type":"max-super-combo","exec":"[63214789][63214789]+[p]","note":"","prereq":"A-ism"}]},{"name":"Evil Ryu","moves":[{"name":"Hadoken","type":"special","exec":"[236]+[p]","note":"","prereq":""},{"name":"Shakunetsu Hadoken","type":"special","exec":"[41236]+[p]","note":"","prereq":""},{"name":"Shoryuken","type":"special","exec":"[623]+[p]","note":"","prereq":""},{"name":"Tatsumaki Zankukyaku ","type":"special","exec":"[214]+[k]","note":"AIR OKAY","prereq":""},{"name":"Ashura Senku","type":"special","exec":"<[623]/[421]>+<[3p]/[3k]>","note":"","prereq":""},{"name":"Shinku Hadoken","type":"super-combo","exec":"[236][236]+[p]","note":"","prereq":"A-ism"},{"name":"Shinku Tatsumaki Senpukyaku","type":"super-combo","exec":"[214][214]+[k]","note":"","prereq":"A-ism"},{"name":"Messatsu Gou Shouryuu","type":"super-combo","exec":"[236][2][3]+[k]","note":"","prereq":"A-ism"},{"name":"Shun Goku Satsu","type":"super-combo","exec":"[lp][lp][6][lk][hp]","note":"","prereq":"X-ism & A-ism"}]},{"name":"Fei Long","moves":[{"name":"Rekkaken","type":"special","exec":"[236]+[p]","note":"Can be executed 3 times in a row","prereq":""},{"name":"Shienkyaku","type":"special","exec":"[421]+[k]","note":"","prereq":""},{"name":"Rekkukyaku","type":"special","exec":"[1][236][9]+[k]","note":"","prereq":"X-ism & V-ism"},{"name":"Rekkashinken","type":"super-combo","exec":"[236][2][3]+[p]","note":"","prereq":"X-ism & A-ism"},{"name":"Shien Renkyaku","type":"super-combo","exec":"[214][214]+[k]","note":"","prereq":"A-ism"},{"name":"Ryuu Yassai","type":"max-super-combo","exec":"[214][214]+[p]","note":"","prereq":"A-ism"}]},{"name":"Gen","moves":[{"name":"Switch to Crane Style","type":"special","exec":"[3k]","note":"","prereq":"Mantis Style & A-ism & V-ism"},{"name":"Hyakurenko","type":"special","exec":"<TAP[p]>","note":"","prereq":"Mantis Style"},{"name":"Gekiro","type":"special","exec":"[623]+[k]","note":"+[k] for followup","prereq":"Mantis Style"},{"name":"Zan'ei","type":"super-combo","exec":"[236][236]+[p]","note":"","prereq":"Mantis Style & X-ism & A-ism"},{"name":"Shitenshuu","type":"super-combo","exec":"[214][214]+[p]","note":"","prereq":"Mantis Style & A-ism"},{"name":"Switch to Mantis Style","type":"special","exec":"[3p]","note":"","prereq":"Crane Style & A-ism & V-ism"},{"name":"Jyasen","type":"special","exec":"[h4][6]+[p]","note":"","prereq":"Crane Style"},{"name":"Oga","type":"special","exec":"[h2][8]+[k]","note":"","prereq":"Crane Style & A-ism & V-ism"},{"name":"Jyakoha","type":"super-combo","exec":"[236][236]+[k]","note":"","prereq":"Crane Style & A-ism"},{"name":"Kouga","type":"super-combo","exec":"<AIR>[214][214]+[k]","note":"","prereq":"Crane Style & A-ism"}]},{"name":"Guile","moves":[{"name":"Sonic Boom","type":"special","exec":"[h4][6]+[p]","note":"","prereq":""},{"name":"Flash Kick","type":"special","exec":"[h2][8]+[k]","note":"","prereq":""},{"name":"Somersault Strike","type":"super-combo","exec":"[h1][3][1][9]+[k]","note":"","prereq":"X-ism & A-ism"},{"name":"Sonic Hurricane","type":"super-combo","exec":"[h4][6][4][6]+[p]<TAP[p]>","note":"","prereq":"A-ism"}]},{"name":"Guy","moves":[{"name":"Hozanto","type":"special","exec":"[214]+[p]","note":"","prereq":""},{"name":"Bushin Senpukyaku","type":"special","exec":"[214]+[k]","note":"","prereq":""},{"name":"Bushin Izuna Drop","type":"special","exec":"[236]+[p]([p])","note":"","prereq":""},{"name":"Hayagake","type":"special","exec":"[236]+[k]","note":"","prereq":""},{"name":"Bushin Muso Renge","type":"super-combo","exec":"[63214][63214]+[p]","note":"","prereq":"X-ism & A-ism"},{"name":"Bushin Hasoken","type":"super-combo","exec":"[236][2][3]+[p]","note":"","prereq":"A-ism"},{"name":"Bushin Gorai Kyaku","type":"super-combo","exec":"[236][2][3]+[k]","note":"","prereq":"A-ism"}]},{"name":"Ingrid","moves":[{"name":"Sunshot","type":"special","exec":"[236]+[p]","note":"","prereq":""},{"name":"Sunrise","type":"special","exec":"[236]+[k]","note":"","prereq":""},{"name":"Sun Arch","type":"special","exec":"[623]+[k]","note":"","prereq":""},{"name":"Sun Upper","type":"special","exec":"[214]+[p]","note":"","prereq":""},{"name":"Sun Lower","type":"special","exec":"[214]+[k]","note":"","prereq":""},{"name":"Sun Dive","type":"special","exec":"<AIR>[214]+[k]","note":"","prereq":""},{"name":"Sunburst","type":"super-combo","exec":"[236][236]+[p]","note":"","prereq":"A-ism"},{"name":"Sunshine","type":"super-combo","exec":"[214][214]+[k]","note":"","prereq":"A-ism"},{"name":"Sun Delta","type":"max-super-combo","exec":"[214][214]+[p]","note":"","prereq":"X-ism & A-ism"}]},{"name":"Juli","moves":[{"name":"Sniping Arrow","type":"special","exec":"[236]+[k]","note":"","prereq":""},{"name":"Cannon Spike","type":"special","exec":"[623]+[k]","note":"","prereq":""},{"name":"Axle Spin Knuckle","type":"special","exec":"[63214]+[p]","note":"","prereq":""},{"name":"Reverse Shaft Breaker","type":"super-combo","exec":"[214][214]+[k](<TAP[p]/[k]>)","note":"","prereq":"X-ism & A-ism"},{"name":"Spin Drive Smasher","type":"super-combo","exec":"[236][2][3]+[k]","note":"","prereq":"A-ism"},{"name":"Psycho Charge Beta","type":"special","exec":"[3p]","note":"Only Usable in Dramatic Battle","prereq":""},{"name":"Psycho Roll","type":"super-combo","exec":"[236][236]+[p]","note":"Only Usable in Dramatic Battle","prereq":"A-ism"},{"name":"Death Cross Dance","type":"max-super-combo","exec":"[lp][lp][6][lk][hp]","note":"Only Usable in Dramatic Battle","prereq":"A-ism"}]},{"name":"Juni","moves":[{"name":"Spiral Arrow","type":"special","exec":"[h4][6]+[k]","note":"AIR OKAY","prereq":""},{"name":"Cannon Spike","type":"special","exec":"[h2][8]+[k]","note":"","prereq":""},{"name":"Mach Slide","type":"special","exec":"[236]+[k]","note":"","prereq":""},{"name":"Cannon Strike","type":"special","exec":"<AIR>[236]+[k]","note":"While Jumping forward","prereq":""},{"name":"Hooligan Combination","type":"special","exec":"[1][236][9]+[p]","note":"","prereq":""},{"name":"Earth Direct","type":"special","exec":"[63214789]+[p]","note":"","prereq":""},{"name":"Psycho Streak","type":"super-combo","exec":"[h4][6][4][6]+[p]","note":"","prereq":"X-ism & A-ism"},{"name":"Spin Drive Smasher","type":"max-super-combo","exec":"[h1][3][1][9]+[k]","note":"","prereq":"A-ism"},{"name":"Psycho Charge Alpha","type":"special","exec":"[3k]","note":"Only Usable in Dramatic Battle","prereq":""},{"name":"Psycho Roll","type":"super-combo","exec":"[236][236]+[p]","note":"Only Usable in Dramatic Battle","prereq":"A-ism"},{"name":"Death Cross Dance","type":"max-super-combo","exec":"[lp][lp][6][lk][hp]","note":"Only Usable in Dramatic Battle","prereq":"A-ism"}]},{"name":"Karin","moves":[{"name":"Guren Ken","type":"special","exec":"[236]+[p]([p])","note":"","prereq":""},{"name":"Hou Shou","type":"special","exec":"[623]+[p]","note":"","prereq":""},{"name":"Mujin Kyaku","type":"special","exec":"[623]+[k]","note":"","prereq":""},{"name":"Ressen Chou","type":"special","exec":"[421]+[p]([p])","note":"","prereq":""},{"name":"Ressen Ha","type":"special","exec":"[1][236][9]+[k]","note":"","prereq":""},{"name":"Yasha Gaeshi - Joudan","type":"special","exec":"[214]+[p]","note":"","prereq":""},{"name":"Yasha Gaeshi - Gedan","type":"special","exec":"[214]+[k]","note":"","prereq":""},{"name":"Arakuma Inashi","type":"special","exec":"[63214789]+[k]","note":"","prereq":""},{"name":"Kanzuki-ryuu Shinpikaibyaku","type":"super-combo","exec":"[236][236]+[p]","note":"","prereq":"X-ism & A-ism"},{"name":"Kanzuki-ryuu Kou'ou Ken","type":"super-combo","exec":"[236][236]+[k]","note":"","prereq":"A-ism"}]},{"name":"Ken","moves":[{"name":"Hadoken","type":"special","exec":"[236]+[p]","note":"","prereq":""},{"name":"Shoryuken","type":"special","exec":"[623]+[p]","note":"","prereq":""},{"name":"Tatsumaki Senpukyaku","type":"special","exec":"[214]+[k]","note":"AIR OKAY","prereq":""},{"name":"Roll","type":"special","exec":"[214]+[p]","note":"","prereq":"A-ism & V-ism"},{"name":"Roll (feint)","type":"special","exec":"[236]+<TAUNT>","note":"","prereq":"A-ism & V-ism"},{"name":"Shoryureppa","type":"super-combo","exec":"[236][2][3]+[p]","note":"","prereq":"X-ism & A-ism"},{"name":"Shinryuken","type":"super-combo","exec":"[236][2][3]+[k](<TAP[p]/[k]>)","note":"","prereq":"A-ism"},{"name":"Shippu Jinraikyaku","type":"super-combo","exec":"[214][214]+[k]","note":"","prereq":"A-ism"}]},{"name":"Maki","moves":[{"name":"Genko","type":"special","exec":"[236]+[p]","note":"","prereq":""},{"name":"Hayagake","type":"special","exec":"[236]+[k]([k])","note":"","prereq":""},{"name":"Saka Hayagake","type":"special","exec":"[214]+[k]([k])","note":"","prereq":""},{"name":"Tengu Daoshi","type":"special","exec":"<AIR>[41236]+[p]","note":"","prereq":""},{"name":"Hassoukyaku","type":"special","exec":"<AIR>[214]+<[p]/[k]>","note":"","prereq":""},{"name":"Reppukyaku","type":"special","exec":"[3p]","note":"","prereq":""},{"name":"Bushin Guraiha","type":"super-combo","exec":"[236][236]+[p]","note":"","prereq":"X-ism & A-ism"},{"name":"Tesshinhou","type":"super-combo","exec":"[236][236]+[k]","note":"","prereq":"A-ism"},{"name":"Ajaratengu","type":"super-combo","exec":"[63214789][63214789]+[p]","note":"AIR OKAY","prereq":""}]},{"name":"M. Bison","moves":[{"name":"Psycho Crusher","type":"special","exec":"[h4][6]+[p]","note":"","prereq":"X-ism"},{"name":"Psycho Shot","type":"special","exec":"[h4][6]+[p]","note":"","prereq":"A-ism & V-ism"},{"name":"Double Knee Press","type":"special","exec":"[h4][6]+[k]","note":"","prereq":""},{"name":"Head Press","type":"special","exec":"[h2][8]+[k]","note":"","prereq":""},{"name":"Devil Reverse","type":"special","exec":"[h2][8]+[p]([p])","note":"","prereq":""},{"name":"Bison Warp","type":"special","exec":"<[623]/[421]>+<[3p]/[3k]>","note":"","prereq":"A-ism & V-ism"},{"name":"Knee Press Nightmare","type":"super-combo","exec":"[h4][6][4][6]+[k]","note":"","prereq":"X-ism & A-ism"},{"name":"Psycho Crusher","type":"super-combo","exec":"[h4][6][4][6]+[p]","note":"","prereq":"A-ism"},{"name":"Ultimate Psycho Crusher","type":"super-combo","exec":"[h4][6][4][6]+[p]","note":"","prereq":"A-ism"}]},{"name":"Rainbow Mika","moves":[{"name":"Flying Peach","type":"special","exec":"[214]+[p]","note":"","prereq":""},{"name":"Shooting Peach","type":"special","exec":"[214]+[k]","note":"","prereq":""},{"name":"Wingless Airplane","type":"special","exec":"<AIR>[63214]+[k]","note":"","prereq":""},{"name":"Paradise Hold","type":"special","exec":"[63214789]+[p]","note":"","prereq":""},{"name":"Daydream Headlock","type":"special","exec":"[63214789]+[k](<TAP[p]/[k]>)","note":"","prereq":""},{"name":"Sardine Beach Special","type":"super-combo","exec":"[236][2][3]+[k]","note":"","prereq":"X-ism & A-ism"},{"name":"Rainbow Hip Rush","type":"super-combo","exec":"[236][2][3]+[p]","note":"","prereq":""},{"name":"Heavenly Dynamite","type":"special","exec":"[63214789][63214789]+[k](<TAP[p]/[k]>)","note":"","prereq":""}]},{"name":"Rolento","moves":[{"name":"Patriot Circle","type":"special","exec":"[236]+[p]","note":"Can be Executed 3 times in a row","prereq":""},{"name":"Stinger","type":"special","exec":"[623]+[k](<[p]/[k]>)","note":"","prereq":""},{"name":"Mekong Delta Air-Raid","type":"special","exec":"[214]+[p]([p])","note":"","prereq":""},{"name":"Mekong Delta Escape","type":"special","exec":"[214]+[k]","note":"","prereq":""},{"name":"Mekong Delta Attack","type":"special","exec":"[3p]([p])","note":"","prereq":""},{"name":"Take No Prisoners","type":"super-combo","exec":"[236][236]+[p]","note":"","prereq":"X-ism & A-ism"},{"name":"Steel Rain","type":"super-combo","exec":"[236][236]+[k]","note":"","prereq":"A-ism"},{"name":"Mine Sweeper","type":"super-combo","exec":"[214][214]+[p]","note":"","prereq":""}]},{"name":"Rose","moves":[{"name":"Soul Spark","type":"special","exec":"[41236]+[p]","note":"","prereq":""},{"name":"Soul Spiral","type":"special","exec":"[236]+[k]","note":"","prereq":""},{"name":"Soul Reflect","type":"special","exec":"[214]+[p]","note":"","prereq":""},{"name":"Soul Throw","type":"special","exec":"[623]+[p]","note":"","prereq":""},{"name":"Aura Soul Throw","type":"super-combo","exec":"[236][236]+[p]","note":"","prereq":"X-ism & A-ism"},{"name":"Soul Illusion","type":"super-combo","exec":"[236][236]+[k]","note":"","prereq":"A-ism"},{"name":"Aura Soul Spark","type":"super-combo","exec":"[214][214]+[p]","note":"","prereq":"A-ism"}]},{"name":"Ryu","moves":[{"name":"Hadoken","type":"special","exec":"[236]+[p]","note":"A-ism version <TAUNT> to feint","prereq":""},{"name":"Shakunetsu Hadoken","type":"special","exec":"[41236]+[p]","note":"","prereq":""},{"name":"Shoryuken","type":"special","exec":"[623]+[p]","note":"","prereq":""},{"name":"Tatsumaki Senpukyaku","type":"special","exec":"[214]+[k]","note":"AIR OKAY","prereq":""},{"name":"Tatsumaki Senpukyaku/Escape","type":"special","exec":"[3][214][7]+[k]","note":"","prereq":""},{"name":"Shinku Hadoken","type":"super-combo","exec":"[236][236]+[p]","note":"","prereq":"X-ism & A-ism"},{"name":"Shinku Tatsumaki Senpukyaku","type":"super-combo","exec":"[214][214]+[k]","note":"","prereq":"A-ism"},{"name":"Metsu/Shin Shoryuken","type":"super-combo","exec":"[236][2][3]+[k]","note":"","prereq":""}]},{"name":"Sagat","moves":[{"name":"High Tiger Shot","type":"special","exec":"[236]+[p]","note":"","prereq":""},{"name":"Low Tiger Shot","type":"special","exec":"[236]+[k]","note":"","prereq":""},{"name":"Tiger Uppercut","type":"special","exec":"[623]+[p]","note":"","prereq":"X-ism"},{"name":"Tiger Blow","type":"special","exec":"[623]+[p]","note":"","prereq":"A-ism & V-ism"},{"name":"Tiger Crush","type":"special","exec":"[1][236][9]+[k]","note":"","prereq":"X-ism"},{"name":"Tiger Crush","type":"special","exec":"[623]+[k]","note":"","prereq":"A-ism & V-ism"},{"name":"Tiger Crush","type":"special","exec":"[1][236][9]+[k]","note":"","prereq":"X-ism"},{"name":"Tiger Genocide","type":"super-combo","exec":"[236][236]+[k]","note":"","prereq":"X-ism & A-ism"},{"name":"Tiger Cannon","type":"super-combo","exec":"[236][236]+[p]","note":"","prereq":"A-ism"},{"name":"Tiger Raid","type":"super-combo","exec":"[214][214]+[k]","note":"","prereq":"A-ism"},{"name":"Angry Charge","type":"special","exec":"[236]+<TAUNT>","note":"","prereq":"A-ism"}]},{"name":"Sakura","moves":[{"name":"Hadoken","type":"special","exec":"[236]+[p]","note":"","prereq":""},{"name":"Shouoken","type":"special","exec":"[623]+[k]","note":"","prereq":""},{"name":"Shunpukyaku","type":"special","exec":"[214]+[k]","note":"AIR OKAY","prereq":""},{"name":"Sakura Otoshi","type":"special","exec":"[623]+[k]([p] up to 3 times)","note":"","prereq":"A-ism & V-ism"},{"name":"Midare Zakura","type":"super-combo","exec":"[236][236]+[k]","note":"","prereq":"X-ism & A-ism"},{"name":"Haru Ichiban","type":"super-combo","exec":"[214][214]+[k]","note":"","prereq":"A-ism"},{"name":"Shinku Hadoken","type":"super-combo","exec":"[236][236]+[p]","note":"","prereq":"A-ism"}]},{"name":"Sodom","moves":[{"name":"Jigoku Scrape","type":"special","exec":"[236]+[p]","note":"","prereq":""},{"name":"Butsu-metsu Buster","type":"special","exec":"[63214789]+[p]","note":"","prereq":""},{"name":"Daikyo Burning","type":"special","exec":"[63214789]+[k]","note":"","prereq":""},{"name":"Shiraha Catch","type":"special","exec":"[623]+[k]","note":"","prereq":""},{"name":"Yagura Reverse","type":"special","exec":"[421]+[k]","note":"","prereq":""},{"name":"Meido no Miyage","type":"super-combo","exec":"[236][236]+[p]","note":"","prereq":"X-ism & A-ism"},{"name":"Tenchusatsu","type":"super-combo","exec":"[63214789][63214789]+[p](<TAP[p]/[k]>)","note":"","prereq":""}]},{"name":"T. Hawk","moves":[{"name":"Mexican Typhoon","type":"special","exec":"[63214789]+[p]","note":"","prereq":""},{"name":"Tomahawk Buster","type":"special","exec":"[623]+[p]","note":"","prereq":""},{"name":"Condor Dive","type":"special","exec":"<AIR>[3p]","note":"","prereq":""},{"name":"Condor Spire","type":"special","exec":"[421]+[p]","note":"","prereq":"A-ism & V-ism"},{"name":"Raging Typhoon","type":"super-combo","exec":"[63214789][63214789]+[p]","note":"","prereq":"X-ism & A-ism"},{"name":"Canyon Splitter","type":"super-combo","exec":"[236][236]+[p]","note":"","prereq":"A-ism"}]},{"name":"Vega","moves":[{"name":"Rolling Crystal Flash","type":"special","exec":"[h4][6]+[p]","note":"","prereq":""},{"name":"Scarlet Terror","type":"special","exec":"[h1][6]+[k]","note":"","prereq":"V-ism"},{"name":"Sky High Claw","type":"special","exec":"[h2][8]+[p]","note":"","prereq":""},{"name":"Flying Barcelona Attack","type":"special","exec":"[h2][8]+[k]([p])","note":"","prereq":""},{"name":"Cage Climb","type":"special","exec":"[h2][8]+[3k]","note":"Vega's stage only","prereq":""},{"name":"Izuna Drop","type":"special","exec":"<[4]/[6]>+[p]","note":"After Flying Barcelona Attack or Cage Climb","prereq":""},{"name":"Flying Barcelona Special","type":"super-combo","exec":"[h1][3][1][9]+[k]","note":"","prereq":"X-ism & A-ism"},{"name":"Super Cage Climb","type":"super-combo","exec":"[h1][3][1][9]+[3k]","note":"Vega's stage only","prereq":"X-ism & A-ism"},{"name":"Rolling Izuna Drop","type":"super-combo","exec":"<[4]/[6]>+[p]","note":"after Flying Barcelona Special or Super Cage Climb","prereq":"X-ism & A-ism"},{"name":"Scarlet Mirage","type":"super-combo","exec":"[h4][6][4][6]+[k]","note":"","prereq":"A-ism"},{"name":"Red Impact","type":"super-combo","exec":"[h4][6][4][6]+[p]","note":"","prereq":"A-ism"}]},{"name":"Yun","moves":[{"name":"Zesshou Hohou","type":"special","exec":"[236]+[p]","note":"","prereq":""},{"name":"Senkyuutai","type":"special","exec":"[236]+[k]","note":"","prereq":"X-ism & V-ism"},{"name":"Kobokushi","type":"special","exec":"[214]+[p]","note":"[2p] to feint","prereq":""},{"name":"Zenpou Tenshin","type":"special","exec":"[63214]+[k]","note":"","prereq":""},{"name":"Tetsuzan Kou","type":"special","exec":"[623]+[p]","note":"","prereq":""},{"name":"Sourai Rengeki","type":"super-combo","exec":"[236][236]+[p]","note":"","prereq":"X-ism & A-ism"},{"name":"You Hou","type":"max-super-combo","exec":"[214][214]+[p]","note":"","prereq":"A-ism"},{"name":"Hiten Souryujin","type":"max-super-combo","exec":"<AIR>[214][214]+[k]","note":"","prereq":"A-ism"}]},{"name":"Zangief","moves":[{"name":"Spinning Piledriver","type":"special","exec":"[63214789]+[p]","note":"","prereq":""},{"name":"Banishing Flat","type":"special","exec":"[6][3][2]+[p]","note":"","prereq":"X-ism"},{"name":"Banishing Flat","type":"special","exec":"[623]+[p]","note":"","prereq":""},{"name":"Double Lariat","type":"special","exec":"<[3p]/[3k]>","note":"","prereq":""},{"name":"Flying Power Bomb/Atomic Suplex","type":"special","exec":"[63214789]+[k]","note":"","prereq":""},{"name":"Final Atomic Buster","type":"super-combo","exec":"[63214789][63214789]+[p]","note":"","prereq":"X-ism & A-ism"},{"name":"Aerial Russian Slam","type":"super-combo","exec":"[236][2][3]+[k]","note":"","prereq":"A-ism"}]}]}
